cwas/__init__.py
cwas/__main__.py
cwas/annotation.py
cwas/argparser.py
cwas/binomial_test.py
cwas/burden_shift.py
cwas/burden_test.py
cwas/categorization.py
cwas/cli.py
cwas/configuration.py
cwas/core/__init__.py
cwas/core/annotation/__init__.py
cwas/core/annotation/bed.py
cwas/core/annotation/vep.py
cwas/core/burden_test/__init__.py
cwas/core/burden_test/binomial.py
cwas/core/categorization/__init__.py
cwas/core/categorization/categorizer.py
cwas/core/categorization/category.py
cwas/core/categorization/parser.py
cwas/core/categorization/utils.py
cwas/core/common.py
cwas/core/configuration/__init__.py
cwas/core/configuration/create.py
cwas/core/configuration/settings.py
cwas/core/dawn/__init__.py
cwas/core/dawn/clustering.py
cwas/core/dawn/supernodeWGS.py
cwas/core/preparation/__init__.py
cwas/core/preparation/annotation.py
cwas/core/preparation/bedreader.py
cwas/correlation.py
cwas/dawn.py
cwas/effective_num_test.py
cwas/env.py
cwas/extract_variant.py
cwas/factory.py
cwas/permutation_test.py
cwas/preparation.py
cwas/risk_score.py
cwas/runnable.py
cwas/start.py
cwas/utils/__init__.py
cwas/utils/check.py
cwas/utils/cmd.py
cwas/utils/log.py
cwas-0.1.8.dist-info/LICENSE
cwas-0.1.8.dist-info/METADATA
cwas-0.1.8.dist-info/WHEEL
cwas-0.1.8.dist-info/entry_points.txt
cwas-0.1.8.dist-info/RECORD
