Metadata-Version: 2.1
Name: cwas
Version: 0.1.8
Summary: Category-wide association study (CWAS). This is a data analytic tool to perform stringent association tests to find non-coding loci associated with autism spectrum disorder (ASD).
Home-page: https://cwas-plus.readthedocs.io/en/latest/
License: MIT
Author: Minwoo Jeong
Author-email: jeongmwj@gmail.com
Maintainer: Yujin Kim
Maintainer-email: yujinkim4896@gmail.com
Requires-Python: >=3.9,<3.13
Classifier: License :: OSI Approved :: MIT License
Classifier: Operating System :: POSIX :: Linux
Classifier: Programming Language :: Python :: 3
Classifier: Programming Language :: Python :: 3.9
Classifier: Programming Language :: Python :: 3.10
Classifier: Programming Language :: Python :: 3.11
Classifier: Programming Language :: Python :: 3.12
Requires-Dist: adjusttext (>=0.8,<0.9)
Requires-Dist: igraph (>=0.10.8,<0.11.0)
Requires-Dist: matplotlib (==3.8.4)
Requires-Dist: numpy (>=1.25.2,<2.0.0)
Requires-Dist: pandas (>=2.1.0,<3.0.0)
Requires-Dist: parmap (>=1.7.0,<2.0.0)
Requires-Dist: polars (>=0.19.2,<0.20.0)
Requires-Dist: pyarrow (>=13,<15)
Requires-Dist: pysam (>=0.22.1,<0.23.0)
Requires-Dist: pytabix (>=0.1,<0.2)
Requires-Dist: pytest (>=7.4.2,<8.0.0)
Requires-Dist: python-dotenv (>=1.0.0,<2.0.0)
Requires-Dist: pyyaml (>=6.0.1,<7.0.0)
Requires-Dist: rpy2 (>=3.5.14,<4.0.0)
Requires-Dist: scanpy (>=1.10.1,<2.0.0)
Requires-Dist: scikit-learn (>=1.3.0,<2.0.0)
Requires-Dist: scipy (==1.13.1)
Requires-Dist: seaborn (>=0.13.2,<0.14.0)
Requires-Dist: setuptools (>=70.0.0,<71.0.0)
Requires-Dist: statsmodels (>=0.14.1,<0.15.0)
Requires-Dist: tqdm (>=4.66.1,<5.0.0)
Requires-Dist: zarr (>=2.16.1,<3.0.0)
Project-URL: Bug Tracker, https://github.com/joonan-lab/cwas/issues
Project-URL: Documentation, https://cwas-plus.readthedocs.io/en/latest/
Project-URL: Repository, https://github.com/joonan-lab/cwas
